mlte/__init__.py
mlte/_private/__init__.py
mlte/_private/file.py
mlte/_private/fixed_json.py
mlte/_private/function_info.py
mlte/_private/hosts.py
mlte/_private/job.py
mlte/_private/meta.py
mlte/_private/platform.py
mlte/_private/reflection.py
mlte/_private/serializing.py
mlte/_private/text.py
mlte/_private/url.py
mlte/_version.py
mlte/artifact/__init__.py
mlte/artifact/artifact.py
mlte/artifact/factory.py
mlte/artifact/model.py
mlte/artifact/type.py
mlte/backend/__init__.py
mlte/backend/api/__init__.py
mlte/backend/api/api.py
mlte/backend/api/auth/__init__.py
mlte/backend/api/auth/authentication.py
mlte/backend/api/auth/authorization.py
mlte/backend/api/auth/http_auth_exception.py
mlte/backend/api/auth/jwt.py
mlte/backend/api/codes.py
mlte/backend/api/endpoints/__init__.py
mlte/backend/api/endpoints/artifact.py
mlte/backend/api/endpoints/catalog_entry.py
mlte/backend/api/endpoints/context.py
mlte/backend/api/endpoints/custom_list_entry.py
mlte/backend/api/endpoints/group.py
mlte/backend/api/endpoints/health.py
mlte/backend/api/endpoints/token.py
mlte/backend/api/endpoints/user.py
mlte/backend/api/error_handlers.py
mlte/backend/api/models/__init__.py
mlte/backend/api/models/artifact_model.py
mlte/backend/api/models/catalog.py
mlte/backend/core/__init__.py
mlte/backend/core/app_factory.py
mlte/backend/core/config.py
mlte/backend/core/state.py
mlte/backend/core/state_stores.py
mlte/backend/main.py
mlte/catalog/__init__.py
mlte/catalog/model.py
mlte/cli/.env.backend
mlte/cli/.env.frontend
mlte/cli/__init__.py
mlte/cli/cli.py
mlte/context/__init__.py
mlte/context/context.py
mlte/context/model.py
mlte/custom_list/__init__.py
mlte/custom_list/custom_list_names.py
mlte/custom_list/model.py
mlte/evidence/__init__.py
mlte/evidence/artifact.py
mlte/evidence/external.py
mlte/evidence/factory.py
mlte/evidence/metadata.py
mlte/evidence/model.py
mlte/evidence/types/__init__.py
mlte/evidence/types/array.py
mlte/evidence/types/image.py
mlte/evidence/types/integer.py
mlte-2.4.0.dist-info/METADATA
mlte-2.4.0.dist-info/WHEEL
mlte-2.4.0.dist-info/entry_points.txt
mlte-2.4.0.dist-info/RECORD
