Metadata-Version: 2.3
Name: mlte
Version: 2.4.0
Summary: An infrastructure for machine learning test and evaluation.
Author: MLTE Engineers
Requires-Python: >=3.9,<3.13
Classifier: Programming Language :: Python :: 3
Classifier: Programming Language :: Python :: 3.9
Classifier: Programming Language :: Python :: 3.10
Classifier: Programming Language :: Python :: 3.11
Classifier: Programming Language :: Python :: 3.12
Provides-Extra: frontend
Provides-Extra: gpu
Provides-Extra: rdbs
Requires-Dist: SQLAlchemy (>=2.0.37) ; extra == "rdbs"
Requires-Dist: SQLAlchemy-Utils (>=0.41.2) ; extra == "rdbs"
Requires-Dist: StrEnum (>=0.4.15)
Requires-Dist: astunparse (>=1.6.3)
Requires-Dist: bcrypt (>=4.2.1)
Requires-Dist: cryptography (>=43.0.3)
Requires-Dist: dill (>=0.3.9)
Requires-Dist: fastapi (>=0.115.6) ; extra == "frontend"
Requires-Dist: httpx (>=0.28.1)
Requires-Dist: json-fix (>=1.0.2)
Requires-Dist: nvidia-ml-py (>=13.580.82) ; extra == "gpu"
Requires-Dist: pint (>=0.24.4)
Requires-Dist: pip-system-certs (>=4.0.0)
Requires-Dist: psutil (>=6.1.1)
Requires-Dist: psycopg2-binary (>=2.9.11) ; extra == "rdbs"
Requires-Dist: pydantic (>=2.10.5)
Requires-Dist: pydantic-settings (>=2.7.1)
Requires-Dist: python-jose (>=3.3.0) ; extra == "frontend"
Requires-Dist: python-multipart (>=0.0.20) ; extra == "frontend"
Requires-Dist: requests (>=2.32.3)
Requires-Dist: uvicorn (>=0.34.0) ; extra == "frontend"
Project-URL: Documentation, https://mlte.readthedocs.io/
Project-URL: Repository, https://github.com/mlte-team/mlte
